ogr_tiller/__init__.py
ogr_tiller/cache_builder.py
ogr_tiller/main.py
ogr_tiller/tiller.py
ogr_tiller/poco/__init__.py
ogr_tiller/poco/job_param.py
ogr_tiller/poco/tileset_manifest.py
ogr_tiller/utils/__init__.py
ogr_tiller/utils/fast_api_utils.py
ogr_tiller/utils/job_utils.py
ogr_tiller/utils/monitor.py
ogr_tiller/utils/ogr_utils.py
ogr_tiller/utils/proj_utils.py
ogr_tiller/utils/sqlite_utils.py
ogr_tiller/utils/stylesheet_utils.py
ogr_tiller/utils/tile_utils.py
ogr_tiller-0.0.54.dist-info/METADATA
ogr_tiller-0.0.54.dist-info/WHEEL
ogr_tiller-0.0.54.dist-info/entry_points.txt
ogr_tiller-0.0.54.dist-info/top_level.txt
ogr_tiller-0.0.54.dist-info/RECORD
