Metadata-Version: 2.1
Name: ogr-tiller
Version: 0.0.54
Summary: Creates vector tiles on the fly from local geopackage files
Home-page: https://github.com/geoyogesh/ogr_tiller
Author: Yogesh Dhanapal
Author-email: geoyogesh@gmail.com
License: GNU-GPL
Classifier: Operating System :: OS Independent
Classifier: Programming Language :: Python :: 3.6
Classifier: Programming Language :: Python :: 3.7
Classifier: Programming Language :: Python :: 3.8
Classifier: Programming Language :: Python :: 3.9
Requires-Dist: fastapi
Requires-Dist: uvicorn[standard]
Requires-Dist: protobuf
Requires-Dist: parse
Requires-Dist: morecantile
Requires-Dist: fiona
Requires-Dist: pyproj
Requires-Dist: pyyaml
Requires-Dist: mapbox-vector-tile (>=2.0.1)
Requires-Dist: rich
